likhithapylib-0.1.0.dist-info/licenses/LICENSE
mylib/__init__.py
mylib/bar_chart.py
mylib/line_plot.py
mylib/scatter_plot.py
likhithapylib-0.1.0.dist-info/METADATA
likhithapylib-0.1.0.dist-info/WHEEL
likhithapylib-0.1.0.dist-info/top_level.txt
likhithapylib-0.1.0.dist-info/RECORD
